nonbond/__init__.py
nonbond/calculator.py
nonbond/coul.py
nonbond/lj.py
nonbond-0.3.0.dist-info/licenses/LICENSE
nonbond-0.3.0.dist-info/METADATA
nonbond-0.3.0.dist-info/WHEEL
nonbond-0.3.0.dist-info/top_level.txt
nonbond-0.3.0.dist-info/RECORD
