Metadata-Version: 2.4
Name: nonbond
Version: 0.3.0
Summary: Add your description here
Requires-Python: >=3.13
License-File: LICENSE
Requires-Dist: ase>=3.26.0
Requires-Dist: torch-pme>=0.3.2
Requires-Dist: vesin-torch>=0.4.2
Dynamic: license-file
